LICENSE
README.rst
setup.py
DETL_PKG/Step.py
DETL_PKG/__init__.py
DETL_PKG/step.py
DETL_PKG.egg-info/PKG-INFO
DETL_PKG.egg-info/SOURCES.txt
DETL_PKG.egg-info/dependency_links.txt
DETL_PKG.egg-info/requires.txt
DETL_PKG.egg-info/top_level.txt