Metadata-Version: 2.1
Name: DETL-PKG
Version: 0.1.6
Summary: A example Python package
Home-page: https://github.com/navinnaik1/DecentETL
Author: navin naik
Author-email: navin.naik@thinkartha.com
License: BSD 2-clause
Classifier: Development Status :: 1 - Planning
Classifier: Intended Audience :: Science/Research
Classifier: License :: OSI Approved :: BSD License
Classifier: Operating System :: POSIX :: Linux
Classifier: Programming Language :: Python :: 2
Classifier: Programming Language :: Python :: 2.7
Classifier: Programming Language :: Python :: 3
Classifier: Programming Language :: Python :: 3.4
Classifier: Programming Language :: Python :: 3.5
License-File: LICENSE
